Metadata-Version: 2.4
Name: llm-provider
Version: 1.0.0
Summary: A unified interface for multiple LLM providers
Home-page: https://github.com/sadikhanecioglu/llm-provider
Author: Sadık Hanecioglu
Author-email: Sadık Hanecioglu <sadikhanecioglu@example.com>
Maintainer-email: Sadık Hanecioglu <sadikhanecioglu@example.com>
License: MIT
Project-URL: Homepage, https://github.com/sadikhanecioglu/llm-provider
Project-URL: Documentation, https://github.com/sadikhanecioglu/llm-provider#readme
Project-URL: Repository, https://github.com/sadikhanecioglu/llm-provider
Project-URL: Bug Tracker, https://github.com/sadikhanecioglu/llm-provider/issues
Keywords: llm,openai,anthropic,gemini,ai,machine learning
Classifier: Development Status :: 4 - Beta
Classifier: Intended Audience :: Developers
Classifier: License :: OSI Approved :: MIT License
Classifier: Operating System :: OS Independent
Classifier: Programming Language :: Python :: 3
Classifier: Programming Language :: Python :: 3.8
Classifier: Programming Language :: Python :: 3.9
Classifier: Programming Language :: Python :: 3.10
Classifier: Programming Language :: Python :: 3.11
Classifier: Programming Language :: Python :: 3.12
Classifier: Topic :: Software Development :: Libraries :: Python Modules
Classifier: Topic :: Scientific/Engineering :: Artificial Intelligence
Requires-Python: >=3.8
Requires-Dist: requests>=2.25.0
Requires-Dist: typing-extensions>=4.0.0; python_version < "3.10"
Provides-Extra: dev
Requires-Dist: pytest>=6.0; extra == "dev"
Requires-Dist: pytest-cov>=2.0; extra == "dev"
Requires-Dist: pytest-asyncio>=0.18.0; extra == "dev"
Requires-Dist: black>=21.0; extra == "dev"
Requires-Dist: isort>=5.0; extra == "dev"
Requires-Dist: flake8>=3.8; extra == "dev"
Requires-Dist: mypy>=0.910; extra == "dev"
Requires-Dist: pre-commit>=2.15; extra == "dev"
Provides-Extra: docs
Requires-Dist: sphinx>=4.0; extra == "docs"
Requires-Dist: sphinx-rtd-theme>=1.0; extra == "docs"
Requires-Dist: myst-parser>=0.17; extra == "docs"
Provides-Extra: all
Requires-Dist: llm-provider[dev,docs]; extra == "all"
